colorclass/__init__.py
colorclass/__main__.py
colorclass/codes.py
colorclass/color.py
colorclass/core.py
colorclass/parse.py
colorclass/search.py
colorclass/toggles.py
colorclass/windows.py
colorclass-2.2.1.dist-info/entry_points.txt
colorclass-2.2.1.dist-info/LICENSE
colorclass-2.2.1.dist-info/WHEEL
colorclass-2.2.1.dist-info/METADATA
colorclass-2.2.1.dist-info/RECORD
