Metadata-Version: 2.1
Name: colorclass
Version: 2.2.1
Summary: Colorful worry-free console applications for Linux, Mac OS X, and Windows.
Home-page: https://github.com/matthewdeanmartin/colorclass
License: MIT
Keywords: Shell,Bash,ANSI,ASCII,terminal,console,colors,automatic
Author: Robpol86
Author-email: robpol86@gmail.com
Requires-Python: >=2.6
Classifier: Development Status :: 5 - Production/Stable
Classifier: Environment :: Console
Classifier: Environment :: MacOS X
Classifier: Environment :: Win32 (MS Windows)
Classifier: Intended Audience :: Developers
Classifier: License :: OSI Approved :: MIT License
Classifier: Operating System :: MacOS :: MacOS X
Classifier: Operating System :: Microsoft :: Windows
Classifier: Operating System :: POSIX
Classifier: Operating System :: POSIX :: Linux
Classifier: Programming Language :: Python :: 2
Classifier: Programming Language :: Python :: 2.6
Classifier: Programming Language :: Python :: 2.7
Classifier: Programming Language :: Python :: 3
Classifier: Programming Language :: Python :: 3.10
Classifier: Programming Language :: Python :: 3.3
Classifier: Programming Language :: Python :: 3.4
Classifier: Programming Language :: Python :: 3.5
Classifier: Programming Language :: Python :: 3.6
Classifier: Programming Language :: Python :: 3.7
Classifier: Programming Language :: Python :: 3.8
Classifier: Programming Language :: Python :: 3.9
Classifier: Programming Language :: Python :: Implementation :: PyPy
Classifier: Topic :: Software Development :: Libraries
Classifier: Topic :: Terminals
Classifier: Topic :: Text Processing :: Markup
Project-URL: Bug Tracker, https://github.com/matthewdeanmartin/colorclass/issues
Project-URL: Change Log, https://github.com/matthewdeanmartin/colorclass/blob/master/CHANGELOG.md
Project-URL: Documentation, https://github.com/matthewdeanmartin/colorclass
Project-URL: Repository, https://github.com/matthewdeanmartin/colorclass
